CHANGELOG.txt
LICENCE.txt
MANIFEST.in
README.md
setup.py
EngimaEncryptionConcept.egg-info/PKG-INFO
EngimaEncryptionConcept.egg-info/SOURCES.txt
EngimaEncryptionConcept.egg-info/dependency_links.txt
EngimaEncryptionConcept.egg-info/top_level.txt
EnigmaEncryption/__init__.py