Metadata-Version: 2.1
Name: EngimaEncryptionConcept
Version: 0.0.5
Summary: Enigma Machine Encryption
Home-page: UNKNOWN
Author: Youwei Zhen
Author-email: anthony20151128@gmail.com
License: MIT
Keywords: encryption
Platform: UNKNOWN
Classifier: Development Status :: 5 - Production/Stable
Classifier: Intended Audience :: Education
Classifier: Operating System :: Microsoft :: Windows :: Windows 10
Classifier: License :: OSI Approved :: MIT License
Classifier: Programming Language :: Python :: 3
